{"page":1,"per_page":20,"total_count":512518,"search_id":"1kyqXMu0fcIC0XRXEYMVDg","data":[{"id":"119484406","added_date":"2012-11-21","aspect":1.0013,"assets":{"huge_jpg":{"display_name":"Small","dpi":72,"file_size":200704,"format":"jpg","height":799,"is_licensable":false,"width":800},"vector_eps":{"display_name":"Vector","format":"eps","is_licensable":true},"preview":{"height":449,"url":"https://image.shutterstock.com/display_pic_with_logo/856843/119484406/stock-vector-cats-collection-vector-silhouette-119484406.jpg","width":450},"small_thumb":{"height":100,"url":"https://thumb9.shutterstock.com/thumb_small/856843/119484406/stock-vector-cats-collection-vector-silhouette-119484406.jpg","width":100},"large_thumb":{"height":150,"url":"https://thumb9.shutterstock.com/thumb_large/856843/119484406/stock-vector-cats-collection-vector-silhouette-119484406.jpg","width":150}},"categories":[{"id":"1","name":"Animals/Wildlife"},{"id":"17","name":"Signs/Symbols"}],"contributor":{"id":"856843"},"description":"Cats collection - vector silhouette","image_type":"vector","is_adult":false,"is_illustration":true,"keywords":["activity","animal","astrology","black","cat","clip art","collage","collection","contour","design","diverse","domestic","drawing","element","feline","female","friend","graphic","group","house cat","icon","illustration","isolated","jumping","kitten","kitty","lying","mammal","outline","pet","playful","pose","posing","pussycat","rest","set","shadow","sign","silhouette","sit","sketch","sleeping","standing","stencil","symbol","tail","vector","walking","woman","zodiac"],"media_type":"image"},{"id":"259729697","added_date":"2015-03-11","aspect":1.5,"assets":{"small_jpg":{"display_name":"Small","dpi":72,"file_size":122880,"format":"jpg","height":333,"is_licensable":true,"width":500},"medium_jpg":{"display_name":"Med","dpi":300,"file_size":401408,"format":"jpg","height":667,"is_licensable":true,"width":1000},"huge_jpg":{"display_name":"Huge","dpi":300,"file_size":3100672,"format":"jpg","height":2400,"is_licensable":true,"width":3600},"supersize_jpg":{"display_name":"Super","dpi":300,"file_size":9567714,"format":"jpg","height":4800,"is_licensable":false,"width":7200},"huge_tiff":{"display_name":"Huge","dpi":300,"file_size":25920000,"format":"tiff","height":2400,"is_licensable":false,"width":3600},"supersize_tiff":{"display_name":"Super","dpi":300,"file_size":103680000,"format":"tiff","height":4800,"is_licensable":false,"width":7200},"preview":{"height":300,"url":"https://image.shutterstock.com/display_pic_with_logo/2856265/259729697/stock-photo-blue-eyed-cat-259729697.jpg","width":450},"small_thumb":{"height":67,"url":"https://thumb10.shutterstock.com/thumb_small/2856265/259729697/stock-photo-blue-eyed-cat-259729697.jpg","width":100},"large_thumb":{"height":100,"url":"https://thumb10.shutterstock.com/thumb_large/2856265/259729697/stock-photo-blue-eyed-cat-259729697.jpg","width":150}},"categories":[{"id":"1","name":"Animals/Wildlife"},{"id":"21","name":"Interiors"}],"contributor":{"id":"2856265"},"description":"Blue eyed Cat","image_type":"photo","is_adult":false,"keywords":["animals","beautiful","blue","cat","cute","eyed","eyes","house","kitten","kitty","little","pets","pussy","white"],"media_type":"image"},{"id":"212180239","added_date":"2014-08-21","aspect":1,"assets":{"huge_jpg":{"display_name":"Small","dpi":72,"file_size":162816,"format":"jpg","height":800,"is_licensable":false,"width":800},"vector_eps":{"display_name":"Vector","format":"eps","is_licensable":true},"preview":{"height":450,"url":"https://image.shutterstock.com/display_pic_with_logo/2064455/212180239/stock-vector-cat-212180239.jpg","width":450},"small_thumb":{"height":100,"url":"https://thumb7.shutterstock.com/thumb_small/2064455/212180239/stock-vector-cat-212180239.jpg","width":100},"large_thumb":{"height":150,"url":"https://thumb7.shutterstock.com/thumb_large/2064455/212180239/stock-vector-cat-212180239.jpg","width":150}},"categories":[{"id":"1","name":"Animals/Wildlife"},{"id":"20","name":"NOT-CATEGORIZED"}],"contributor":{"id":"2064455"},"description":"cat","image_type":"vector","is_adult":false,"is_illustration":true,"keywords":["angora","animal","blue","bombay","cat","colorful","cute","forest","illustration","isolated","kitten","manx","norwegian","pet","russian","siamese","simple","sphynx","turkish","vector"],"media_type":"image"},{"id":"116906134","added_date":"2012-10-28","aspect":1.4983,"assets":{"small_jpg":{"display_name":"Small","dpi":72,"file_size":136192,"format":"jpg","height":334,"is_licensable":true,"width":500},"medium_jpg":{"display_name":"Med","dpi":300,"file_size":503808,"format":"jpg","height":667,"is_licensable":true,"width":1000},"huge_jpg":{"display_name":"Huge","dpi":300,"file_size":8527872,"format":"jpg","height":3771,"is_licensable":true,"width":5650},"huge_tiff":{"display_name":"Huge","dpi":300,"file_size":63918450,"format":"tiff","height":3771,"is_licensable":false,"width":5650},"preview":{"height":300,"url":"https://image.shutterstock.com/display_pic_with_logo/562036/116906134/stock-photo-portrait-of-brown-eyed-cat-isolated-on-white-background-116906134.jpg","width":450},"small_thumb":{"height":67,"url":"https://thumb1.shutterstock.com/thumb_small/562036/116906134/stock-photo-portrait-of-brown-eyed-cat-isolated-on-white-background-116906134.jpg","width":100},"large_thumb":{"height":100,"url":"https://thumb1.shutterstock.com/thumb_large/562036/116906134/stock-photo-portrait-of-brown-eyed-cat-isolated-on-white-background-116906134.jpg","width":150}},"categories":[{"id":"1","name":"Animals/Wildlife"},{"id":"20","name":"NOT-CATEGORIZED"}],"contributor":{"id":"562036"},"description":"Portrait of brown-eyed cat isolated on white background","image_type":"photo","is_adult":false,"keywords":["adorable","animal","background","beautiful","brown","carnivore","cat","close","close-up","cut-out","cute","cutout","domestic","eyes","feline","female","fluffy","full","fur","gold","hair","isolated","kitten","kitty","lie","looking","mammal","one","orange","paw","pet","playful","portrait","posing","pretty","purebred","rest","shorthair","small","stare","strike","striking","striped","studio","tabby","tail","view","whisker","white","woman","young"],"media_type":"image"},{"id":"302691488","added_date":"2015-08-03","aspect":1.1289,"assets":{"small_jpg":{"display_name":"Small","dpi":72,"file_size":160768,"format":"jpg","height":443,"is_licensable":true,"width":500},"medium_jpg":{"display_name":"Med","dpi":300,"file_size":566272,"format":"jpg","height":886,"is_licensable":true,"width":1000},"huge_jpg":{"display_name":"Huge","dpi":300,"file_size":6953984,"format":"jpg","height":4189,"is_licensable":true,"width":4729},"huge_tiff":{"display_name":"Huge","dpi":300,"file_size":59429343,"format":"tiff","height":4189,"is_licensable":false,"width":4729},"preview":{"height":398,"url":"https://image.shutterstock.com/display_pic_with_logo/139051/302691488/stock-photo-funny-cats-self-picture-selfie-stick-in-his-hand-couple-of-cat-taking-a-selfie-together-with-302691488.jpg","width":450},"small_thumb":{"height":89,"url":"https://thumb1.shutterstock.com/thumb_small/139051/302691488/stock-photo-funny-cats-self-picture-selfie-stick-in-his-hand-couple-of-cat-taking-a-selfie-together-with-302691488.jpg","width":100},"large_thumb":{"height":133,"url":"https://thumb1.shutterstock.com/thumb_large/139051/302691488/stock-photo-funny-cats-self-picture-selfie-stick-in-his-hand-couple-of-cat-taking-a-selfie-together-with-302691488.jpg","width":150}},"categories":[{"id":"1","name":"Animals/Wildlife"},{"id":"16","name":"Technology"}],"contributor":{"id":"139051"},"description":"Funny cats - Self picture. Selfie stick in his hand.\nCouple of cat taking a selfie together with smartphone camera","image_type":"photo","is_adult":false,"keywords":["animal","cam","camera","cat","cell","cheerful","close","companion","couple","digital","embrace","friend","friendship","fun","funny","happiness","happy","hug","humor","instagram","joke","joy","kitty","laugh","lens","lifestyle","love","lovers","mobile","pet","phone","photo","photographer","photography","picture","portrait","self","self-portrait","selfie","shot","smart","smile","snapshot","stick","take","telephone","together","tourist"],"media_type":"image"},{"id":"309581141","added_date":"2015-08-25","aspect":1.0552,"assets":{"huge_jpg":{"display_name":"Small","dpi":72,"file_size":67584,"format":"jpg","height":580,"is_licensable":false,"width":612},"vector_eps":{"display_name":"Vector","format":"eps","is_licensable":true},"preview":{"height":426,"url":"https://image.shutterstock.com/display_pic_with_logo/709774/309581141/stock-vector-cute-cat-illustration-series-309581141.jpg","width":450},"small_thumb":{"height":95,"url":"https://thumb7.shutterstock.com/thumb_small/709774/309581141/stock-vector-cute-cat-illustration-series-309581141.jpg","width":100},"large_thumb":{"height":142,"url":"https://thumb7.shutterstock.com/thumb_large/709774/309581141/stock-vector-cute-cat-illustration-series-309581141.jpg","width":150}},"categories":[{"id":"1","name":"Animals/Wildlife"},{"id":"27","name":"Beauty/Fashion"}],"contributor":{"id":"709774"},"description":"cute cat illustration series","image_type":"vector","is_adult":false,"is_illustration":true,"keywords":["abstract","anger","animal","awe","beautiful","big","black","cartoon","cat","chinese","collection","design","domestic","doodle","drawing","feline","fluffy","fun","grace","humor","illustration","ink","isolated","joy","kitten","large","lazy","mammal","outline","paw","pencil","pets","set","silhouette","simplicity","sketch","smile","striped","style","sunglasses","symbol","tail","text","thick","vector","whisker","white"],"media_type":"image"},{"id":"161832497","added_date":"2013-11-07","aspect":1.5,"assets":{"small_jpg":{"display_name":"Small","dpi":72,"file_size":186368,"format":"jpg","height":333,"is_licensable":true,"width":500},"medium_jpg":{"display_name":"Med","dpi":300,"file_size":681984,"format":"jpg","height":667,"is_licensable":true,"width":1000},"huge_jpg":{"display_name":"Huge","dpi":300,"file_size":12494848,"format":"jpg","height":3456,"is_licensable":true,"width":5184},"huge_tiff":{"display_name":"Huge","dpi":300,"file_size":53747712,"format":"tiff","height":3456,"is_licensable":false,"width":5184},"preview":{"height":300,"url":"https://image.shutterstock.com/display_pic_with_logo/847993/161832497/stock-photo-close-up-cat-and-dog-together-lying-on-the-floor-161832497.jpg","width":450},"small_thumb":{"height":67,"url":"https://thumb10.shutterstock.com/thumb_small/847993/161832497/stock-photo-close-up-cat-and-dog-together-lying-on-the-floor-161832497.jpg","width":100},"large_thumb":{"height":100,"url":"https://thumb10.shutterstock.com/thumb_large/847993/161832497/stock-photo-close-up-cat-and-dog-together-lying-on-the-floor-161832497.jpg","width":150}},"categories":[{"id":"1","name":"Animals/Wildlife"},{"id":"22","name":"Miscellaneous"}],"contributor":{"id":"847993"},"description":"close up, cat and dog together lying on the floor","image_type":"photo","is_adult":false,"keywords":["animal","background","beautiful","brown","canine","cat","cute","dog","domestic","feline","friend","friendly","friendship","funny","german","happy","kitten","laying","love","pedigreed","pet","portrait","puppy","resting","shepherd","together","togetherness","young"],"media_type":"image"},{"id":"132272738","added_date":"2013-03-20","aspect":0.9963,"assets":{"huge_jpg":{"display_name":"Small","dpi":72,"file_size":117760,"format":"jpg","height":800,"is_licensable":false,"width":797},"vector_eps":{"display_name":"Vector","format":"eps","is_licensable":true},"preview":{"height":450,"url":"https://image.shutterstock.com/display_pic_with_logo/1294618/132272738/stock-vector-silhouettes-of-cats-132272738.jpg","width":448},"small_thumb":{"height":100,"url":"https://thumb1.shutterstock.com/thumb_small/1294618/132272738/stock-vector-silhouettes-of-cats-132272738.jpg","width":100},"large_thumb":{"height":150,"url":"https://thumb1.shutterstock.com/thumb_large/1294618/132272738/stock-vector-silhouettes-of-cats-132272738.jpg","width":149}},"categories":[{"id":"1","name":"Animals/Wildlife"},{"id":"12","name":"Nature"}],"contributor":{"id":"1294618"},"description":"silhouettes of cats","image_type":"vector","is_adult":false,"is_illustration":true,"keywords":["animal","art","awesome","bad","beast","black","cat","character","clip","contour","cute","dark","decorative","drawing","elegance","female","force","graphic","hunter","icon","idea","illustration","image","independence","isolated","kitten","lines","luck","nature","pet","pic","picture","predator","pussy","shape","sign","silhouette","simplicity","simplified","symbol","tail","tattoo","thoroughbred","tomcat","vector","vet","woman","young"],"media_type":"image"},{"id":"138599810","added_date":"2013-05-15","aspect":0.6666,"assets":{"small_jpg":{"display_name":"Small","dpi":72,"file_size":138240,"format":"jpg","height":500,"is_licensable":true,"width":333},"medium_jpg":{"display_name":"Med","dpi":300,"file_size":494592,"format":"jpg","height":1000,"is_licensable":true,"width":667},"huge_jpg":{"display_name":"Huge","dpi":300,"file_size":3208192,"format":"jpg","height":3404,"is_licensable":true,"width":2269},"supersize_jpg":{"display_name":"Super","dpi":300,"file_size":10801232,"format":"jpg","height":6808,"is_licensable":false,"width":4538},"huge_tiff":{"display_name":"Huge","dpi":300,"file_size":23171028,"format":"tiff","height":3404,"is_licensable":false,"width":2269},"supersize_tiff":{"display_name":"Super","dpi":300,"file_size":92684112,"format":"tiff","height":6808,"is_licensable":false,"width":4538},"preview":{"height":450,"url":"https://image.shutterstock.com/display_pic_with_logo/429748/138599810/stock-photo-red-male-cat-walking-towards-camera-isolated-in-white-138599810.jpg","width":299},"small_thumb":{"height":100,"url":"https://thumb1.shutterstock.com/thumb_small/429748/138599810/stock-photo-red-male-cat-walking-towards-camera-isolated-in-white-138599810.jpg","width":67},"large_thumb":{"height":150,"url":"https://thumb1.shutterstock.com/thumb_large/429748/138599810/stock-photo-red-male-cat-walking-towards-camera-isolated-in-white-138599810.jpg","width":100}},"categories":[{"id":"1","name":"Animals/Wildlife"},{"id":"12","name":"Nature"}],"contributor":{"id":"429748"},"description":"red male cat, walking towards camera, isolated in white","image_type":"photo","is_adult":false,"keywords":["agog","alone","animal","cat","companion","creature","curiosity","curious","cut out","domestic","facing","front view","inquisitive","isolated on white","looking at the camera","mammal","one animal","pet","portrait","red","standing","studio shot","white background"],"media_type":"image"},{"id":"278842925","added_date":"2015-05-17","aspect":1.5,"assets":{"small_jpg":{"display_name":"Small","dpi":72,"file_size":153600,"format":"jpg","height":333,"is_licensable":true,"width":500},"medium_jpg":{"display_name":"Med","dpi":300,"file_size":491520,"format":"jpg","height":667,"is_licensable":true,"width":1000},"huge_jpg":{"display_name":"Huge","dpi":300,"file_size":7974912,"format":"jpg","height":3744,"is_licensable":true,"width":5616},"huge_tiff":{"display_name":"Huge","dpi":300,"file_size":63078912,"format":"tiff","height":3744,"is_licensable":false,"width":5616},"preview":{"height":300,"url":"https://image.shutterstock.com/display_pic_with_logo/154447/278842925/stock-photo-a-ginger-cat-sleeps-in-his-soft-cozy-bed-on-a-floor-carpet-soft-focus-278842925.jpg","width":450},"small_thumb":{"height":67,"url":"https://thumb7.shutterstock.com/thumb_small/154447/278842925/stock-photo-a-ginger-cat-sleeps-in-his-soft-cozy-bed-on-a-floor-carpet-soft-focus-278842925.jpg","width":100},"large_thumb":{"height":100,"url":"https://thumb7.shutterstock.com/thumb_large/154447/278842925/stock-photo-a-ginger-cat-sleeps-in-his-soft-cozy-bed-on-a-floor-carpet-soft-focus-278842925.jpg","width":150}},"categories":[{"id":"1","name":"Animals/Wildlife"},{"id":"20","name":"NOT-CATEGORIZED"}],"contributor":{"id":"154447"},"description":"A ginger cat sleeps in his soft cozy bed on a floor carpet, soft focus","image_type":"photo","is_adult":false,"keywords":["adorable","animal","basket","bed","carpet","cat","close","closeup","comfort","comfortable","cozy","cute","feline","floor","fluffy","focus","funny","ginger","high","home","kitty","lovable","lying","nap","orange","pet","pose","red","relax","rest","resting","sleeping","soft","top","up","warm"],"media_type":"image"},{"id":"235089946","added_date":"2014-12-03","aspect":1.4998,"assets":{"small_jpg":{"display_name":"Small","dpi":72,"file_size":167936,"format":"jpg","height":333,"is_licensable":true,"width":500},"medium_jpg":{"display_name":"Med","dpi":300,"file_size":450560,"format":"jpg","height":667,"is_licensable":true,"width":1000},"huge_jpg":{"display_name":"Huge","dpi":300,"file_size":5099520,"format":"jpg","height":2667,"is_licensable":true,"width":4000},"supersize_jpg":{"display_name":"Super","dpi":300,"file_size":12228098,"format":"jpg","height":5334,"is_licensable":false,"width":8000},"huge_tiff":{"display_name":"Huge","dpi":300,"file_size":32004000,"format":"tiff","height":2667,"is_licensable":false,"width":4000},"supersize_tiff":{"display_name":"Super","dpi":300,"file_size":128016000,"format":"tiff","height":5334,"is_licensable":false,"width":8000},"preview":{"height":300,"url":"https://image.shutterstock.com/display_pic_with_logo/154447/235089946/stock-photo-cute-little-red-kitten-sleeps-on-fur-white-blanket-235089946.jpg","width":450},"small_thumb":{"height":67,"url":"https://thumb9.shutterstock.com/thumb_small/154447/235089946/stock-photo-cute-little-red-kitten-sleeps-on-fur-white-blanket-235089946.jpg","width":100},"large_thumb":{"height":100,"url":"https://thumb9.shutterstock.com/thumb_large/154447/235089946/stock-photo-cute-little-red-kitten-sleeps-on-fur-white-blanket-235089946.jpg","width":150}},"categories":[{"id":"1","name":"Animals/Wildlife"}],"contributor":{"id":"154447"},"description":"Cute little red kitten sleeps on fur white blanket","image_type":"photo","is_adult":false,"keywords":["adorable","animal","baby","blanket","cat","child","close","closeup","comfort","comfortable","cozy","cream","cute","domestic","feline","fluffy","funny","fur","furry","ginger","hair","high","kitten","kitty","little","looking","lovable","lying","one","orange","paw","pet","portrait","pose","pussy","red","relax","relaxation","rest","resting","shorthair","sleeping","small","soft","top","up","warm","white","yellow","young"],"media_type":"image"},{"id":"226315111","added_date":"2014-10-27","aspect":1.1111,"assets":{"huge_jpg":{"display_name":"Huge","dpi":300,"file_size":1617920,"format":"jpg","height":4500,"is_licensable":false,"width":5000},"vector_eps":{"display_name":"Vector","format":"eps","is_licensable":true},"preview":{"height":405,"url":"https://image.shutterstock.com/display_pic_with_logo/868231/226315111/stock-vector-set-of-cute-cartoon-kitties-or-cats-with-different-colored-fur-and-markings-standing-sitting-or-226315111.jpg","width":450},"small_thumb":{"height":90,"url":"https://thumb7.shutterstock.com/thumb_small/868231/226315111/stock-vector-set-of-cute-cartoon-kitties-or-cats-with-different-colored-fur-and-markings-standing-sitting-or-226315111.jpg","width":100},"large_thumb":{"height":135,"url":"https://thumb7.shutterstock.com/thumb_large/868231/226315111/stock-vector-set-of-cute-cartoon-kitties-or-cats-with-different-colored-fur-and-markings-standing-sitting-or-226315111.jpg","width":150}},"categories":[{"id":"1","name":"Animals/Wildlife"},{"id":"17","name":"Signs/Symbols"}],"contributor":{"id":"868231"},"description":"Set of cute cartoon kitties or cats with different colored fur and markings standing  sitting or walking  vector illustrations on grey","image_type":"vector","is_adult":false,"is_illustration":true,"has_property_release":true,"keywords":["alert","animal","background","black","breeds","calico","carnivore","cartoon","cats","clipart","collection","colored","colors","companion","cute","design","different","domestic","elements","feline","friend","fur","ginger","grey","hunter","icons","kids","kitties","loyal","lying","markings","marmalade","nine","nocturnal","pedigree","pet","predator","profile","set","siamese","sitting","standing","tabby","vector","walking"],"media_type":"image"},{"id":"114350371","added_date":"2012-10-01","aspect":1.4555,"assets":{"small_jpg":{"display_name":"Small","dpi":72,"file_size":143360,"format":"jpg","height":344,"is_licensable":true,"width":500},"medium_jpg":{"display_name":"Med","dpi":300,"file_size":549888,"format":"jpg","height":687,"is_licensable":true,"width":1000},"huge_jpg":{"display_name":"Huge","dpi":300,"file_size":3250176,"format":"jpg","height":2136,"is_licensable":true,"width":3109},"supersize_jpg":{"display_name":"Super","dpi":300,"file_size":11880489,"format":"jpg","height":4272,"is_licensable":false,"width":6218},"huge_tiff":{"display_name":"Huge","dpi":300,"file_size":19922472,"format":"tiff","height":2136,"is_licensable":false,"width":3109},"supersize_tiff":{"display_name":"Super","dpi":300,"file_size":79689888,"format":"tiff","height":4272,"is_licensable":false,"width":6218},"preview":{"height":309,"url":"https://image.shutterstock.com/display_pic_with_logo/428239/114350371/stock-photo-the-dog-and-cat-lie-together-isolated-on-white-background-114350371.jpg","width":450},"small_thumb":{"height":69,"url":"https://thumb7.shutterstock.com/thumb_small/428239/114350371/stock-photo-the-dog-and-cat-lie-together-isolated-on-white-background-114350371.jpg","width":100},"large_thumb":{"height":103,"url":"https://thumb7.shutterstock.com/thumb_large/428239/114350371/stock-photo-the-dog-and-cat-lie-together-isolated-on-white-background-114350371.jpg","width":150}},"categories":[{"id":"1","name":"Animals/Wildlife"},{"id":"27","name":"Beauty/Fashion"}],"contributor":{"id":"428239"},"description":"the dog and cat lie together. isolated on white background","image_type":"photo","is_adult":false,"keywords":["adorable","adult","animal","background","beautiful","beauty","brown","canine","care","cat","close up","couple","cute","dog","down","embrace","face","family","female","friendly","friends","friendship","fun","funny","group","hound","hug","isolated","kitten","kitty","lie","life","little","love","lovely","maine coon","muzzle","opposites","paw","pet","playing","portrait","puppy","sad","together","togetherness","two","whelp","white","woman","young","youth"],"media_type":"image"},{"id":"113021647","added_date":"2012-09-17","aspect":1,"assets":{"small_jpg":{"display_name":"Small","dpi":72,"file_size":107520,"format":"jpg","height":500,"is_licensable":true,"width":500},"medium_jpg":{"display_name":"Med","dpi":300,"file_size":369664,"format":"jpg","height":1000,"is_licensable":true,"width":1000},"huge_jpg":{"display_name":"Huge","dpi":300,"file_size":1751040,"format":"jpg","height":2800,"is_licensable":true,"width":2800},"supersize_jpg":{"display_name":"Super","dpi":300,"file_size":5375041,"format":"jpg","height":5600,"is_licensable":false,"width":5600},"huge_tiff":{"display_name":"Huge","dpi":300,"file_size":23520000,"format":"tiff","height":2800,"is_licensable":false,"width":2800},"supersize_tiff":{"display_name":"Super","dpi":300,"file_size":94080000,"format":"tiff","height":5600,"is_licensable":false,"width":5600},"preview":{"height":450,"url":"https://image.shutterstock.com/display_pic_with_logo/689443/113021647/stock-photo-small-gray-kitten-isolated-on-white-background-113021647.jpg","width":450},"small_thumb":{"height":100,"url":"https://thumb10.shutterstock.com/thumb_small/689443/113021647/stock-photo-small-gray-kitten-isolated-on-white-background-113021647.jpg","width":100},"large_thumb":{"height":150,"url":"https://thumb10.shutterstock.com/thumb_large/689443/113021647/stock-photo-small-gray-kitten-isolated-on-white-background-113021647.jpg","width":150}},"categories":[{"id":"1","name":"Animals/Wildlife"},{"id":"9","name":"Objects"}],"contributor":{"id":"689443"},"description":"Small gray kitten isolated on white background","image_type":"photo","is_adult":false,"keywords":["animals","background","brown","cat","chartreux","cut","cute","domestic","eyes","feline","fluffy","front","fur","gray","grey","indoors","isolated","kitten","looking","lying","mammal","nature","nobody","one","pets","playing","portrait","posing","purebred","shot","sitting","space","standing","vertical","view","whisker","white","young"],"media_type":"image"},{"id":"142870015","added_date":"2013-06-19","aspect":1.5,"assets":{"small_jpg":{"display_name":"Small","dpi":72,"file_size":202752,"format":"jpg","height":333,"is_licensable":true,"width":500},"medium_jpg":{"display_name":"Med","dpi":300,"file_size":740352,"format":"jpg","height":667,"is_licensable":true,"width":1000},"huge_jpg":{"display_name":"Huge","dpi":300,"file_size":15722496,"format":"jpg","height":3744,"is_licensable":true,"width":5616},"huge_tiff":{"display_name":"Huge","dpi":300,"file_size":63078912,"format":"tiff","height":3744,"is_licensable":false,"width":5616},"preview":{"height":300,"url":"https://image.shutterstock.com/display_pic_with_logo/95962/142870015/stock-photo-bengal-cat-142870015.jpg","width":450},"small_thumb":{"height":67,"url":"https://thumb7.shutterstock.com/thumb_small/95962/142870015/stock-photo-bengal-cat-142870015.jpg","width":100},"large_thumb":{"height":100,"url":"https://thumb7.shutterstock.com/thumb_large/95962/142870015/stock-photo-bengal-cat-142870015.jpg","width":150}},"categories":[{"id":"1","name":"Animals/Wildlife"},{"id":"12","name":"Nature"}],"contributor":{"id":"95962"},"description":"Bengal cat","image_type":"photo","is_adult":false,"keywords":["animal","background","beautiful","bengal","breed","cat","curious","cute","domestic","feline","funny","fur","ginger","hair","household","kitten","kitty","leopard","paw","pedigree","pedigreed","pet","playful","portrait","purebred","puss","shorthair","spot","striped","tabby","veterinarian","whiskers","young"],"media_type":"image"},{"id":"325858112","added_date":"2015-10-10","aspect":1.5,"assets":{"small_jpg":{"display_name":"Small","dpi":72,"file_size":172032,"format":"jpg","height":333,"is_licensable":true,"width":500},"medium_jpg":{"display_name":"Med","dpi":300,"file_size":620544,"format":"jpg","height":667,"is_licensable":true,"width":1000},"huge_jpg":{"display_name":"Huge","dpi":300,"file_size":3281920,"format":"jpg","height":2016,"is_licensable":true,"width":3024},"supersize_jpg":{"display_name":"Super","dpi":300,"file_size":10444158,"format":"jpg","height":4032,"is_licensable":false,"width":6048},"huge_tiff":{"display_name":"Huge","dpi":300,"file_size":18289152,"format":"tiff","height":2016,"is_licensable":false,"width":3024},"supersize_tiff":{"display_name":"Super","dpi":300,"file_size":73156608,"format":"tiff","height":4032,"is_licensable":false,"width":6048},"preview":{"height":300,"url":"https://image.shutterstock.com/display_pic_with_logo/154447/325858112/stock-photo-young-woman-wearing-warm-sweater-is-resting-with-a-cat-on-the-armchair-at-home-one-autumn-day-325858112.jpg","width":450},"small_thumb":{"height":67,"url":"https://thumb9.shutterstock.com/thumb_small/154447/325858112/stock-photo-young-woman-wearing-warm-sweater-is-resting-with-a-cat-on-the-armchair-at-home-one-autumn-day-325858112.jpg","width":100},"large_thumb":{"height":100,"url":"https://thumb9.shutterstock.com/thumb_large/154447/325858112/stock-photo-young-woman-wearing-warm-sweater-is-resting-with-a-cat-on-the-armchair-at-home-one-autumn-day-325858112.jpg","width":150}},"categories":[{"id":"1","name":"Animals/Wildlife"},{"id":"13","name":"People"}],"contributor":{"id":"154447"},"description":"Young woman wearing warm sweater is resting with a cat on the armchair at home one autumn day","image_type":"photo","is_adult":false,"has_model_release":true,"keywords":["animal","armchair","autumn","beautiful","care","casual","cat","chair","cheerful","cold","comfortable","cozy","domestic","fall","feelings","ginger","happy","home","house","human","indoor","interior","kitten","knit","life","lifestyle","living","love","owner","pet","playing","relax","resting","sitting","still","sweater","warm","winter","woman"],"media_type":"image","models":[{"id":"15486652"}]},{"id":"266348171","added_date":"2015-04-04","aspect":1,"assets":{"huge_jpg":{"display_name":"Small","dpi":72,"file_size":76800,"format":"jpg","height":600,"is_licensable":false,"width":600},"vector_eps":{"display_name":"Vector","format":"eps","is_licensable":true},"preview":{"height":450,"url":"https://image.shutterstock.com/display_pic_with_logo/202783/266348171/stock-vector-set-of-cats-silhouettes-on-a-white-background-266348171.jpg","width":450},"small_thumb":{"height":100,"url":"https://thumb7.shutterstock.com/thumb_small/202783/266348171/stock-vector-set-of-cats-silhouettes-on-a-white-background-266348171.jpg","width":100},"large_thumb":{"height":150,"url":"https://thumb7.shutterstock.com/thumb_large/202783/266348171/stock-vector-set-of-cats-silhouettes-on-a-white-background-266348171.jpg","width":150}},"categories":[{"id":"9","name":"Objects"},{"id":"12","name":"Nature"}],"contributor":{"id":"202783"},"description":"Set of cats Silhouettes on a white background.","image_type":"vector","is_adult":false,"is_illustration":true,"has_property_release":true,"keywords":["animal","black","body","cartoon","cat","collection","cut","design","domestic","element","feline","group","illustration","image","isolated","kitten","large","mammal","objects","on","out","outline","paw","pets","set","shape","silhouette","sitting","sketch","stealth","tail","vector","white"],"media_type":"image"},{"id":"125480678","added_date":"2013-01-22","aspect":1,"assets":{"small_jpg":{"display_name":"Small","dpi":72,"file_size":185344,"format":"jpg","height":500,"is_licensable":true,"width":500},"medium_jpg":{"display_name":"Med","dpi":300,"file_size":686080,"format":"jpg","height":1000,"is_licensable":true,"width":1000},"huge_jpg":{"display_name":"Huge","dpi":300,"file_size":2946048,"format":"jpg","height":2832,"is_licensable":true,"width":2832},"supersize_jpg":{"display_name":"Super","dpi":300,"file_size":9257699,"format":"jpg","height":5664,"is_licensable":false,"width":5664},"huge_tiff":{"display_name":"Huge","dpi":300,"file_size":24060672,"format":"tiff","height":2832,"is_licensable":false,"width":2832},"supersize_tiff":{"display_name":"Super","dpi":300,"file_size":96242688,"format":"tiff","height":5664,"is_licensable":false,"width":5664},"preview":{"height":450,"url":"https://image.shutterstock.com/display_pic_with_logo/438058/125480678/stock-photo-little-gray-kitten-portrait-up-isolated-on-white-background-125480678.jpg","width":450},"small_thumb":{"height":100,"url":"https://thumb1.shutterstock.com/thumb_small/438058/125480678/stock-photo-little-gray-kitten-portrait-up-isolated-on-white-background-125480678.jpg","width":100},"large_thumb":{"height":150,"url":"https://thumb1.shutterstock.com/thumb_large/438058/125480678/stock-photo-little-gray-kitten-portrait-up-isolated-on-white-background-125480678.jpg","width":150}},"categories":[{"id":"1","name":"Animals/Wildlife"},{"id":"12","name":"Nature"}],"contributor":{"id":"438058"},"description":"Little gray kitten portrait up isolated on white background.","image_type":"photo","is_adult":false,"keywords":["adorable","animal","baby","background","beautiful","breed","camera","cat","curious","cut","cute","domestic","eyes","feline","fun","funny","fur","furry","gray","grey","hair","isolated","kitten","kitty","looking","mammal","nature","one","pet","playful","playing","portrait","posing","pretty","shorthair","shot","small","space","striped","studio","sweet","view","whiskers","white","young"],"media_type":"image"},{"id":"309105233","added_date":"2015-08-24","aspect":1,"assets":{"huge_jpg":{"display_name":"Med","dpi":300,"file_size":454656,"format":"jpg","height":1667,"is_licensable":false,"width":1667},"vector_eps":{"display_name":"Vector","format":"eps","is_licensable":true},"preview":{"height":450,"url":"https://image.shutterstock.com/display_pic_with_logo/2064455/309105233/stock-vector-cats-309105233.jpg","width":450},"small_thumb":{"height":100,"url":"https://thumb10.shutterstock.com/thumb_small/2064455/309105233/stock-vector-cats-309105233.jpg","width":100},"large_thumb":{"height":150,"url":"https://thumb10.shutterstock.com/thumb_large/2064455/309105233/stock-vector-cats-309105233.jpg","width":150}},"categories":[{"id":"1","name":"Animals/Wildlife"},{"id":"20","name":"NOT-CATEGORIZED"}],"contributor":{"id":"2064455"},"description":"Cats","image_type":"vector","is_adult":false,"is_illustration":true,"keywords":["acting","box","cat","colorful","cute","flat","grooming","illustration","isolated","play","set","simple","stretch","vector"],"media_type":"image"},{"id":"91233320","added_date":"2011-12-21","aspect":5.0997,"assets":{"small_jpg":{"display_name":"Small","dpi":72,"file_size":57344,"format":"jpg","height":98,"is_licensable":true,"width":500},"medium_jpg":{"display_name":"Med","dpi":300,"file_size":179200,"format":"jpg","height":196,"is_licensable":true,"width":1000},"huge_jpg":{"display_name":"Huge","dpi":300,"file_size":37616640,"format":"jpg","height":4632,"is_licensable":true,"width":23622},"huge_tiff":{"display_name":"Huge","dpi":300,"file_size":328251312,"format":"tiff","height":4632,"is_licensable":false,"width":23622},"preview":{"height":88,"url":"https://image.shutterstock.com/display_pic_with_logo/85920/85920,1324363098,1/stock-photo-group-of-cats-and-dogs-in-front-of-white-background-91233320.jpg","width":450},"small_thumb":{"height":20,"url":"https://thumb7.shutterstock.com/thumb_small/85920/85920,1324363098,1/stock-photo-group-of-cats-and-dogs-in-front-of-white-background-91233320.jpg","width":100},"large_thumb":{"height":29,"url":"https://thumb7.shutterstock.com/thumb_large/85920/85920,1324363098,1/stock-photo-group-of-cats-and-dogs-in-front-of-white-background-91233320.jpg","width":150}},"categories":[{"id":"1","name":"Animals/Wildlife"},{"id":"0","name":"Transportation"}],"contributor":{"id":"85920"},"description":"Group of cats and dogs in front of white background","image_type":"photo","is_adult":false,"keywords":["alert","alertness","attentive","breed","brown","canine","cat","companionship","copy space","creature","cut-out","cutout","dog","domestic","domestic animal","feline","five animals","front view","full length","group","horizontal","in a row","indoors","isolated","isolated on white","large group of animals","laying","lined up","lizard","looking","looking at camera","lying","mammal","panorama","parrot","pedigree","pedigreed","pet","purebred","row","sitting","species","studio shot","tan","white background"],"media_type":"image"}]}